driftbench/__init__.py
driftbench/benchmarks/__init__.py
driftbench/benchmarks/data.py
driftbench/data_generation/__init__.py
driftbench/data_generation/data_generator.py
driftbench/data_generation/drifts.py
driftbench/data_generation/latent_information.py
driftbench/data_generation/loaders.py
driftbench/data_generation/sample.py
driftbench/data_generation/solvers.py
driftbench/data_generation/visualize.py
driftbench/drift_detection/__init__.py
driftbench/drift_detection/detectors.py
driftbench/drift_detection/helpers.py
driftbench/drift_detection/metrics.py
driftbench-0.0.14.dist-info/LICENSE
driftbench-0.0.14.dist-info/METADATA
driftbench-0.0.14.dist-info/WHEEL
driftbench-0.0.14.dist-info/top_level.txt
driftbench-0.0.14.dist-info/RECORD
