Metadata-Version: 2.1
Name: driftbench
Version: 0.0.14
Summary: Python tool to analyse process drifts
Home-page: 
Author: Edgar Wolf
Author-email: Edgar Wolf <edgar.wolf@hs-kempten.de>, Tobias Windisch <tobias.windisch@hs-kempten.de>
Maintainer-email: Edgar Wolf <edgar.wolf@hs-kempten.de>
License-File: LICENSE
Requires-Dist: jaxlib
Requires-Dist: jax
Requires-Dist: matplotlib==3.7.2
Requires-Dist: numpy==1.24.4
Requires-Dist: pandas==2.0.3
Requires-Dist: scikit-learn==1.3.0
Requires-Dist: scipy==1.12.0
Requires-Dist: setuptools==68.1.2
Requires-Dist: torch>=1.13.1
Requires-Dist: pyyaml
Provides-Extra: cuda
Requires-Dist: jax[cuda]; extra == "cuda"
Provides-Extra: dev
Requires-Dist: pytest; extra == "dev"
Requires-Dist: mkdocs; extra == "dev"
Requires-Dist: mkdocs-material; extra == "dev"
Requires-Dist: mkdocstrings-python; extra == "dev"
Requires-Dist: mike; extra == "dev"
